Workbook

Sheet Cover
B2: LEVERAGED BUYOUT ANALYSIS
B4: [Target Company]
B6: Confidential - For Discussion Purposes Only
B9: TRANSACTION SUMMARY
B11: Date | D11: February 04, 2026
B12: Transaction Type | D12: Leveraged Buyout
B13: Sponsor | D13: [Sponsor Name]
B14: Target | D14: [Target Company]
B15: Entry EV | D15: $XXX.X million
B16: Entry Multiple | D16: X.Xx LTM EBITDA
B17: Equity Check | D17: $XX.X million
B18: Hold Period | D18: 5 years

Sheet Assumptions
A1: MODEL ASSUMPTIONS
A3: TRANSACTION ASSUMPTIONS
A4: Assumption | B4: Value | C4: Units
A5: Transaction Date | B5: 2025-12-31 | C5: Date
A6: LTM Revenue ($M) | B6: 500 | C6: Currency
A7: LTM EBITDA ($M) | B7: 75 | C7: Currency
A8: LTM EBITDA Margin | B8: 0.15 | C8: Percent
A9: Entry EV/EBITDA Multiple | B9: 8 | C9: Multiple
A11: Transaction Fees (% of EV) | B11: 0.02 | C11: Percent
A12: Financing Fees (% of Debt) | B12: 0.025 | C12: Percent
A13: Minimum Cash Balance ($M) | B13: 10 | C13: Currency
A15: CAPITAL STRUCTURE
A16: Debt Tranche | B16: Multiple | C16: Rate | D16: Amort | E16: Term
A17: Senior Secured (Term Loan B) | B17: 3.5 | C17: 0.065 | D17: 0.01 | E17: 7
A18: Second Lien | B18: 1 | C18: 0.095 | D18: 0 | E18: 8
A19: Subordinated / Mezzanine | B19: 0.5 | C19: 0.12 | D19: 0 | E19: 10
A22: OPERATING ASSUMPTIONS
A23: Driver | B23: Year 1 | C23: Year 2 | D23: Year 3 | E23: Year 4 | F23: Year 5
A24: Revenue Growth | B24: 0.08 | C24: 0.07 | D24: 0.06 | E24: 0.05 | F24: 0.05
A25: EBITDA Margin | B25: 0.16 | C25: 0.17 | D25: 0.18 | E25: 0.18 | F25: 0.19
A26: D&A % Revenue | B26: 0.03 | C26: 0.03 | D26: 0.03 | E26: 0.03 | F26: 0.03
A27: CapEx % Revenue | B27: 0.04 | C27: 0.04 | D27: 0.03 | E27: 0.03 | F27: 0.03
A28: NWC % Revenue | B28: 0.1 | C28: 0.1 | D28: 0.1 | E28: 0.1 | F28: 0.1
A29: Tax Rate | B29: 0.25 | C29: 0.25 | D29: 0.25 | E29: 0.25 | F29: 0.25
A32: EXIT ASSUMPTIONS
A33: Exit Year | B33: 5 | C33: Year
A34: Exit EV/EBITDA Multiple | B34: 8 | C34: Multiple
A35: Exit Multiple vs Entry | B35: 0 | C35: Delta

Sheet Sources & Uses
A1: SOURCES AND USES OF FUNDS
A2: ($ in millions)
A4: SOURCES OF FUNDS
A5: Source | B5: Amount | C5: Multiple | D5: % of Total
A6: Senior Secured Term Loan B | B6: =Assumptions!B19*Assumptions!B7 | C6: =B6/Assumptions!$B$7 | D6: =B6/$B$15
A7: Second Lien Term Loan | B7: =Assumptions!B20*Assumptions!B7 | C7: =B7/Assumptions!$B$7 | D7: =B7/$B$15
A8: Subordinated Debt | B8: =Assumptions!B21*Assumptions!B7 | C8: =B8/Assumptions!$B$7 | D8: =B8/$B$15
A9: Rollover Equity | B9: 0 | C9: =B9/Assumptions!$B$7 | D9: =B9/$B$15
A10: Sponsor Equity | B10: =B15-SUM(B6:B9) | C10: =B10/Assumptions!$B$7 | D10: =B10/$B$15
A11: Total Sources | B11: =SUM(B6:B10) | C11: =B11/Assumptions!$B$7 | D11: =1
A13: USES OF FUNDS
A14: Use | B14: Amount | C14: Multiple | D14: % of Total
A15: Purchase Enterprise Value | B15: =Assumptions!B9*Assumptions!B7 | C15: =B15/Assumptions!$B$7 | D15: =B15/$B$15
A16: Refinance Existing Debt | B16: 0 | C16: =B16/Assumptions!$B$7 | D16: =B16/$B$15
A17: Transaction Fees | B17: =Assumptions!B11*B15 | C17: =B17/Assumptions!$B$7 | D17: =B17/$B$15
A18: Financing Fees | B18: =Assumptions!B12*(B6+B7+B8) | C18: =B18/Assumptions!$B$7 | D18: =B18/$B$15
A19: Cash to Balance Sheet | B19: =Assumptions!B13 | C19: =B19/Assumptions!$B$7 | D19: =B19/$B$15
A20: Total Uses | B20: =SUM(B15:B19) | C20: =B20/Assumptions!$B$7 | D20: =1
A22: Sources - Uses (Check) | B22: =B15-B20

Sheet Operating Model
A1: OPERATING MODEL
A2: ($ in millions, fiscal year ending December 31)
B4: LTM | C4: Year 1 | D4: Year 2 | E4: Year 3 | F4: Year 4 | G4: Year 5
A5: INCOME STATEMENT
A6: Revenue | B6: =Assumptions!B6 | C6: =B6*(1+Assumptions!C28) | D6: =C6*(1+Assumptions!D28) | E6: =D6*(1+Assumptions!E28) | F6: =E6*(1+Assumptions!F28) | G6: =F6*(1+Assumptions!G28)
A7: % Growth | C7: =(C6-B6)/B6 | D7: =(D6-C6)/C6 | E7: =(E6-D6)/D6 | F7: =(F6-E6)/E6 | G7: =(G6-F6)/F6
A9: EBITDA | B9: =Assumptions!B7 | C9: =C6*Assumptions!C29 | D9: =D6*Assumptions!D29 | E9: =E6*Assumptions!E29 | F9: =F6*Assumptions!F29 | G9: =G6*Assumptions!G29
A10: % Margin | B10: =B9/B6 | C10: =C9/C6 | D10: =D9/D6 | E10: =E9/E6 | F10: =F9/F6 | G10: =G9/G6
A12: D&A | B12: =B6*Assumptions!B30 | C12: =C6*Assumptions!C30 | D12: =D6*Assumptions!D30 | E12: =E6*Assumptions!E30 | F12: =F6*Assumptions!F30 | G12: =G6*Assumptions!G30
A13: EBIT | B13: =B9-B12 | C13: =C9-C12 | D13: =D9-D12 | E13: =E9-E12 | F13: =F9-F12 | G13: =G9-G12
A14: % Margin | B14: =B13/B6 | C14: =C13/C6 | D14: =D13/D6 | E14: =E13/E6 | F14: =F13/F6 | G14: =G13/G6
A16: Interest Expense | C16: ='Debt Schedule'!C25 | D16: ='Debt Schedule'!D25 | E16: ='Debt Schedule'!E25 | F16: ='Debt Schedule'!F25 | G16: ='Debt Schedule'!G25
A17: EBT | B17: =B13 | C17: =C13-C16 | D17: =D13-D16 | E17: =E13-E16 | F17: =F13-F16 | G17: =G13-G16
A18: Taxes | B18: =B17*0.25 | C18: =MAX(0,C17)*Assumptions!C33 | D18: =MAX(0,D17)*Assumptions!D33 | E18: =MAX(0,E17)*Assumptions!E33 | F18: =MAX(0,F17)*Assumptions!F33 | G18: =MAX(0,G17)*Assumptions!G33
A19: Net Income | B19: =B17-B18 | C19: =C17-C18 | D19: =D17-D18 | E19: =E17-E18 | F19: =F17-F18 | G19: =G17-G18
A21: FREE CASH FLOW
A22: EBITDA | C22: =C9 | D22: =D9 | E22: =E9 | F22: =F9 | G22: =G9
A23: (-) Cash Taxes | C23: =-C18 | D23: =-D18 | E23: =-E18 | F23: =-F18 | G23: =-G18
A24: (-) CapEx | C24: =-C6*Assumptions!C31 | D24: =-D6*Assumptions!D31 | E24: =-E6*Assumptions!E31 | F24: =-F6*Assumptions!F31 | G24: =-G6*Assumptions!G31
A25: (+/-) Change in NWC | C25: =-(C6*Assumptions!C32-B6*Assumptions!B32) | D25: =-(D6*Assumptions!D32-C6*Assumptions!C32) | E25: =-(E6*Assumptions!E32-D6*Assumptions!D32) | F25: =-(F6*Assumptions!F32-E6*Assumptions!E32) | G25: =-(G6*Assumptions!G32-F6*Assumptions!F32)
A26: Unlevered Free Cash Flow | C26: =SUM(C22:C25) | D26: =SUM(D22:D25) | E26: =SUM(E22:E25) | F26: =SUM(F22:F25) | G26: =SUM(G22:G25)
A28: (-) Cash Interest | C28: =-C16 | D28: =-D16 | E28: =-E16 | F28: =-F16 | G28: =-G16
A29: (-) Mandatory Amortization | C29: ='Debt Schedule'!C19 | D29: ='Debt Schedule'!D19 | E29: ='Debt Schedule'!E19 | F29: ='Debt Schedule'!F19 | G29: ='Debt Schedule'!G19
A30: Free Cash Flow for Debt Paydown | C30: =C26+C28+C29 | D30: =D26+D28+D29 | E30: =E26+E28+E29 | F30: =F26+F28+F29 | G30: =G26+G28+G29

Sheet Debt Schedule
A1: DEBT SCHEDULE
A2: ($ in millions)
B4: Entry | C4: Year 1 | D4: Year 2 | E4: Year 3 | F4: Year 4 | G4: Year 5
A5: SENIOR SECURED TERM LOAN B
A6: Beginning Balance | B6: 0 | C6: =B10 | D6: =C10 | E6: =D10 | F6: =E10 | G6: =F10
A7: (+) Draws | B7: ='Sources & Uses'!B6 | C7: 0 | D7: 0 | E7: 0 | F7: 0 | G7: 0
A8: (-) Mandatory Amortization | B8: 0 | C8: =-C6*Assumptions!D19 | D8: =-D6*Assumptions!D19 | E8: =-E6*Assumptions!D19 | F8: =-F6*Assumptions!D19 | G8: =-G6*Assumptions!D19
A9: (-) Optional Prepayment | B9: 0 | C9: 0 | D9: 0 | E9: 0 | F9: 0 | G9: 0
A10: Ending Balance | B10: =MAX(0,B6+B7+B8+B9) | C10: =MAX(0,C6+C7+C8+C9) | D10: =MAX(0,D6+D7+D8+D9) | E10: =MAX(0,E6+E7+E8+E9) | F10: =MAX(0,F6+F7+F8+F9) | G10: =MAX(0,G6+G7+G8+G9)
A12: Interest Rate | B12: =Assumptions!C19 | C12: =Assumptions!C19 | D12: =Assumptions!C19 | E12: =Assumptions!C19 | F12: =Assumptions!C19 | G12: =Assumptions!C19
A13: Interest Expense | B13: =B10*B12 | C13: =(B10+C10)/2*C12 | D13: =(C10+D10)/2*D12 | E13: =(D10+E10)/2*E12 | F13: =(E10+F10)/2*F12 | G13: =(F10+G10)/2*G12
A15: SECOND LIEN TERM LOAN
A16: Beginning Balance | B16: 0 | C16: =B19 | D16: =C19 | E16: =D19 | F16: =E19 | G16: =F19
A17: (+) Draws | B17: ='Sources & Uses'!B7 | C17: 0 | D17: 0 | E17: 0 | F17: 0 | G17: 0
A18: (-) Amortization | B18: 0 | C18: 0 | D18: 0 | E18: 0 | F18: 0 | G18: 0
A19: Ending Balance | B19: =MAX(0,B16+B17+B18) | C19: =MAX(0,C16+C17+C18) | D19: =MAX(0,D16+D17+D18) | E19: =MAX(0,E16+E17+E18) | F19: =MAX(0,F16+F17+F18) | G19: =MAX(0,G16+G17+G18)
A21: Interest Rate | B21: =Assumptions!C20 | C21: =Assumptions!C20 | D21: =Assumptions!C20 | E21: =Assumptions!C20 | F21: =Assumptions!C20 | G21: =Assumptions!C20
A22: Interest Expense | B22: =B20*B21 | C22: =(B20+C20)/2*C21 | D22: =(C20+D20)/2*D21 | E22: =(D20+E20)/2*E21 | F22: =(E20+F20)/2*F21 | G22: =(F20+G20)/2*G21
A24: TOTAL DEBT SUMMARY
A25: Total Debt | B25: =B10+B19 | C25: =C10+C19 | D25: =D10+D19 | E25: =E10+E19 | F25: =F10+F19 | G25: =G10+G19
A26: Total Interest Expense | B26: =B13+B22 | C26: =C13+C22 | D26: =D13+D22 | E26: =E13+E22 | F26: =F13+F22 | G26: =G13+G22

Sheet Returns Analysis
A1: LBO RETURNS ANALYSIS
A2: ($ in millions)
A4: EXIT ANALYSIS
A5: Exit Year | B5: =Assumptions!B35
A6: Exit EBITDA | B6: ='Operating Model'!G9
A7: Exit Multiple | B7: =Assumptions!B36
A8: Exit Enterprise Value | B8: =B6*B7
A9: (-) Net Debt at Exit | B9: ='Debt Schedule'!G24
A10: Exit Equity Value | B10: =B8-B9
A13: RETURNS SUMMARY
A14: Initial Equity Investment | B14: ='Sources & Uses'!B10
A15: Exit Equity Value | B15: =B10
A16: Total Equity Gain | B16: =B15-B14
A18: MOIC (Multiple on Invested Capital) | B18: =B10/B14
A19: IRR (Internal Rate of Return) | B19: =(B10/B14)^(1/Assumptions!B35)-1
A22: SENSITIVITY ANALYSIS
A24: MOIC: Entry Multiple vs Exit Multiple
B25: Exit Multiple
A26: Entry | B26: 6 | C26: 7 | D26: 8 | E26: 9 | F26: 10
A27: 6 | B27: =6.0/6.0*B18 | C27: =7.0/6.0*B18 | D27: =8.0/6.0*B18 | E27: =9.0/6.0*B18 | F27: =10.0/6.0*B18
A28: 7 | B28: =6.0/7.0*B18 | C28: =7.0/7.0*B18 | D28: =8.0/7.0*B18 | E28: =9.0/7.0*B18 | F28: =10.0/7.0*B18
A29: 8 | B29: =6.0/8.0*B18 | C29: =7.0/8.0*B18 | D29: =8.0/8.0*B18 | E29: =9.0/8.0*B18 | F29: =10.0/8.0*B18
A30: 9 | B30: =6.0/9.0*B18 | C30: =7.0/9.0*B18 | D30: =8.0/9.0*B18 | E30: =9.0/9.0*B18 | F30: =10.0/9.0*B18
A31: 10 | B31: =6.0/10.0*B18 | C31: =7.0/10.0*B18 | D31: =8.0/10.0*B18 | E31: =9.0/10.0*B18 | F31: =10.0/10.0*B18
